[{"name":"data class Left<out L>(left: L) : Either<L, Nothing> ","description":"com.javiersc.either.Either.Left","location":"projects/either-core/com.javiersc.either/-either/-left/index.html","searchKeys":["Left","data class Left<out L>(left: L) : Either<L, Nothing> ","com.javiersc.either.Either.Left"]},{"name":"data class Right<out R>(right: R) : Either<Nothing, R> ","description":"com.javiersc.either.Either.Right","location":"projects/either-core/com.javiersc.either/-either/-right/index.html","searchKeys":["Right","data class Right<out R>(right: R) : Either<Nothing, R> ","com.javiersc.either.Either.Right"]},{"name":"fun <L, R> L.asLeft(): Either<L, R>","description":"com.javiersc.either.extensions.asLeft","location":"projects/either-core/com.javiersc.either.extensions/as-left.html","searchKeys":["asLeft","fun <L, R> L.asLeft(): Either<L, R>","com.javiersc.either.extensions.asLeft"]},{"name":"fun <L, R> Pair<L, R>.asLeft(): Either<L, R>","description":"com.javiersc.either.extensions.asLeft","location":"projects/either-core/com.javiersc.either.extensions/as-left.html","searchKeys":["asLeft","fun <L, R> Pair<L, R>.asLeft(): Either<L, R>","com.javiersc.either.extensions.asLeft"]},{"name":"fun <L, R> Pair<L, R>.asRight(): Either<L, R>","description":"com.javiersc.either.extensions.asRight","location":"projects/either-core/com.javiersc.either.extensions/as-right.html","searchKeys":["asRight","fun <L, R> Pair<L, R>.asRight(): Either<L, R>","com.javiersc.either.extensions.asRight"]},{"name":"fun <L, R> R.asRight(): Either<L, R>","description":"com.javiersc.either.extensions.asRight","location":"projects/either-core/com.javiersc.either.extensions/as-right.html","searchKeys":["asRight","fun <L, R> R.asRight(): Either<L, R>","com.javiersc.either.extensions.asRight"]},{"name":"fun <out L> Left(left: L)","description":"com.javiersc.either.Either.Left.Left","location":"projects/either-core/com.javiersc.either/-either/-left/-left.html","searchKeys":["Left","fun <out L> Left(left: L)","com.javiersc.either.Either.Left.Left"]},{"name":"fun <out R> Right(right: R)","description":"com.javiersc.either.Either.Right.Right","location":"projects/either-core/com.javiersc.either/-either/-right/-right.html","searchKeys":["Right","fun <out R> Right(right: R)","com.javiersc.either.Either.Right.Right"]},{"name":"inline fun <L, R, NL, NR> Either<L, R>.map(left: (L) -> NL, right: (R) -> NR): Either<NL, NR>","description":"com.javiersc.either.extensions.map","location":"projects/either-core/com.javiersc.either.extensions/map.html","searchKeys":["map","inline fun <L, R, NL, NR> Either<L, R>.map(left: (L) -> NL, right: (R) -> NR): Either<NL, NR>","com.javiersc.either.extensions.map"]},{"name":"inline fun <L, R, NL> Either<L, R>.mapLeft(left: (L) -> NL): Either<NL, R>","description":"com.javiersc.either.extensions.mapLeft","location":"projects/either-core/com.javiersc.either.extensions/map-left.html","searchKeys":["mapLeft","inline fun <L, R, NL> Either<L, R>.mapLeft(left: (L) -> NL): Either<NL, R>","com.javiersc.either.extensions.mapLeft"]},{"name":"inline fun <L, R, NR> Either<L, R>.mapRight(right: (R) -> NR): Either<L, NR>","description":"com.javiersc.either.extensions.mapRight","location":"projects/either-core/com.javiersc.either.extensions/map-right.html","searchKeys":["mapRight","inline fun <L, R, NR> Either<L, R>.mapRight(right: (R) -> NR): Either<L, NR>","com.javiersc.either.extensions.mapRight"]},{"name":"inline fun <L, R> Either<L, R>.combine(either: Either<L, R>, left: (L, L) -> L, right: (R, R) -> R): Either<L, R>","description":"com.javiersc.either.extensions.combine","location":"projects/either-core/com.javiersc.either.extensions/combine.html","searchKeys":["combine","inline fun <L, R> Either<L, R>.combine(either: Either<L, R>, left: (L, L) -> L, right: (R, R) -> R): Either<L, R>","com.javiersc.either.extensions.combine"]},{"name":"inline fun <L, R> Either<L, R>.fold(left: (L) -> Unit, right: (R) -> Unit)","description":"com.javiersc.either.extensions.fold","location":"projects/either-core/com.javiersc.either.extensions/fold.html","searchKeys":["fold","inline fun <L, R> Either<L, R>.fold(left: (L) -> Unit, right: (R) -> Unit)","com.javiersc.either.extensions.fold"]},{"name":"inline fun <L1, R1, L2, R2, R, L> Either<L1, R1>.combine(another: Either<L2, R2>, left: (L1, L2) -> L, thisLeft: (L1) -> L, anotherLeft: (L2) -> L, right: (R1, R2) -> R): Either<L, R>","description":"com.javiersc.either.extensions.combine","location":"projects/either-core/com.javiersc.either.extensions/combine.html","searchKeys":["combine","inline fun <L1, R1, L2, R2, R, L> Either<L1, R1>.combine(another: Either<L2, R2>, left: (L1, L2) -> L, thisLeft: (L1) -> L, anotherLeft: (L2) -> L, right: (R1, R2) -> R): Either<L, R>","com.javiersc.either.extensions.combine"]},{"name":"sealed class Either<out L, out R>","description":"com.javiersc.either.Either","location":"projects/either-core/com.javiersc.either/-either/index.html","searchKeys":["Either","sealed class Either<out L, out R>","com.javiersc.either.Either"]},{"name":"val left: L","description":"com.javiersc.either.Either.Left.left","location":"projects/either-core/com.javiersc.either/-either/-left/left.html","searchKeys":["left","val left: L","com.javiersc.either.Either.Left.left"]},{"name":"val right: R","description":"com.javiersc.either.Either.Right.right","location":"projects/either-core/com.javiersc.either/-either/-right/right.html","searchKeys":["right","val right: R","com.javiersc.either.Either.Right.right"]},{"name":"class NetworkEitherCallAdapterFactory(isNetworkAvailable: () -> Boolean) : CallAdapter.Factory","description":"com.javiersc.either.network.NetworkEitherCallAdapterFactory","location":"projects/network/network-core/com.javiersc.either.network/-network-either-call-adapter-factory/index.html","searchKeys":["NetworkEitherCallAdapterFactory","class NetworkEitherCallAdapterFactory(isNetworkAvailable: () -> Boolean) : CallAdapter.Factory","com.javiersc.either.network.NetworkEitherCallAdapterFactory"]},{"name":"class NetworkEitherKtor(client: HttpClient)","description":"com.javiersc.either.network.ktor.NetworkEitherKtor","location":"projects/network/network-core/com.javiersc.either.network.ktor/-network-either-ktor/index.html","searchKeys":["NetworkEitherKtor","class NetworkEitherKtor(client: HttpClient)","com.javiersc.either.network.ktor.NetworkEitherKtor"]},{"name":"data class Http<F>(error: F, code: HttpStatusCode, headers: Headers) : Failure<F> ","description":"com.javiersc.either.network.Failure.Http","location":"projects/network/network-core/com.javiersc.either.network/-failure/-http/index.html","searchKeys":["Http","data class Http<F>(error: F, code: HttpStatusCode, headers: Headers) : Failure<F> ","com.javiersc.either.network.Failure.Http"]},{"name":"data class HttpStatusCode(value: Int)","description":"com.javiersc.either.network.HttpStatusCode","location":"projects/network/network-core/com.javiersc.either.network/-http-status-code/index.html","searchKeys":["HttpStatusCode","data class HttpStatusCode(value: Int)","com.javiersc.either.network.HttpStatusCode"]},{"name":"data class Success<S>(data: S, code: HttpStatusCode, headers: Headers)","description":"com.javiersc.either.network.Success","location":"projects/network/network-core/com.javiersc.either.network/-success/index.html","searchKeys":["Success","data class Success<S>(data: S, code: HttpStatusCode, headers: Headers)","com.javiersc.either.network.Success"]},{"name":"data class Unknown(throwable: Throwable) : Failure<Nothing> ","description":"com.javiersc.either.network.Failure.Unknown","location":"projects/network/network-core/com.javiersc.either.network/-failure/-unknown/index.html","searchKeys":["Unknown","data class Unknown(throwable: Throwable) : Failure<Nothing> ","com.javiersc.either.network.Failure.Unknown"]},{"name":"fun <F, S> buildNetworkFailureHttp(error: F, code: HttpStatusCode, headers: Headers): NetworkEither<F, S>","description":"com.javiersc.either.network.buildNetworkFailureHttp","location":"projects/network/network-core/com.javiersc.either.network/build-network-failure-http.html","searchKeys":["buildNetworkFailureHttp","fun <F, S> buildNetworkFailureHttp(error: F, code: HttpStatusCode, headers: Headers): NetworkEither<F, S>","com.javiersc.either.network.buildNetworkFailureHttp"]},{"name":"fun <F, S> buildNetworkFailureLocal(): NetworkEither<F, S>","description":"com.javiersc.either.network.buildNetworkFailureLocal","location":"projects/network/network-core/com.javiersc.either.network/build-network-failure-local.html","searchKeys":["buildNetworkFailureLocal","fun <F, S> buildNetworkFailureLocal(): NetworkEither<F, S>","com.javiersc.either.network.buildNetworkFailureLocal"]},{"name":"fun <F, S> buildNetworkFailureRemote(): NetworkEither<F, S>","description":"com.javiersc.either.network.buildNetworkFailureRemote","location":"projects/network/network-core/com.javiersc.either.network/build-network-failure-remote.html","searchKeys":["buildNetworkFailureRemote","fun <F, S> buildNetworkFailureRemote(): NetworkEither<F, S>","com.javiersc.either.network.buildNetworkFailureRemote"]},{"name":"fun <F, S> buildNetworkFailureUnknown(throwable: Throwable): NetworkEither<F, S>","description":"com.javiersc.either.network.buildNetworkFailureUnknown","location":"projects/network/network-core/com.javiersc.either.network/build-network-failure-unknown.html","searchKeys":["buildNetworkFailureUnknown","fun <F, S> buildNetworkFailureUnknown(throwable: Throwable): NetworkEither<F, S>","com.javiersc.either.network.buildNetworkFailureUnknown"]},{"name":"fun <F, S> buildNetworkSuccess(data: S, code: HttpStatusCode, headers: Headers): NetworkEither<F, S>","description":"com.javiersc.either.network.buildNetworkSuccess","location":"projects/network/network-core/com.javiersc.either.network/build-network-success.html","searchKeys":["buildNetworkSuccess","fun <F, S> buildNetworkSuccess(data: S, code: HttpStatusCode, headers: Headers): NetworkEither<F, S>","com.javiersc.either.network.buildNetworkSuccess"]},{"name":"fun <F> Http(error: F, code: HttpStatusCode, headers: Headers)","description":"com.javiersc.either.network.Failure.Http.Http","location":"projects/network/network-core/com.javiersc.either.network/-failure/-http/-http.html","searchKeys":["Http","fun <F> Http(error: F, code: HttpStatusCode, headers: Headers)","com.javiersc.either.network.Failure.Http.Http"]},{"name":"fun <S> Success(data: S, code: HttpStatusCode, headers: Headers)","description":"com.javiersc.either.network.Success.Success","location":"projects/network/network-core/com.javiersc.either.network/-success/-success.html","searchKeys":["Success","fun <S> Success(data: S, code: HttpStatusCode, headers: Headers)","com.javiersc.either.network.Success.Success"]},{"name":"fun HttpStatusCode(value: Int)","description":"com.javiersc.either.network.HttpStatusCode.HttpStatusCode","location":"projects/network/network-core/com.javiersc.either.network/-http-status-code/-http-status-code.html","searchKeys":["HttpStatusCode","fun HttpStatusCode(value: Int)","com.javiersc.either.network.HttpStatusCode.HttpStatusCode"]},{"name":"fun NetworkEitherCallAdapterFactory(isNetworkAvailable: () -> Boolean = { internalIsNetworkAvailable })","description":"com.javiersc.either.network.NetworkEitherCallAdapterFactory.NetworkEitherCallAdapterFactory","location":"projects/network/network-core/com.javiersc.either.network/-network-either-call-adapter-factory/-network-either-call-adapter-factory.html","searchKeys":["NetworkEitherCallAdapterFactory","fun NetworkEitherCallAdapterFactory(isNetworkAvailable: () -> Boolean = { internalIsNetworkAvailable })","com.javiersc.either.network.NetworkEitherCallAdapterFactory.NetworkEitherCallAdapterFactory"]},{"name":"fun NetworkEitherKtor(client: HttpClient)","description":"com.javiersc.either.network.ktor.NetworkEitherKtor.NetworkEitherKtor","location":"projects/network/network-core/com.javiersc.either.network.ktor/-network-either-ktor/-network-either-ktor.html","searchKeys":["NetworkEitherKtor","fun NetworkEitherKtor(client: HttpClient)","com.javiersc.either.network.ktor.NetworkEitherKtor.NetworkEitherKtor"]},{"name":"fun Unknown(throwable: Throwable)","description":"com.javiersc.either.network.Failure.Unknown.Unknown","location":"projects/network/network-core/com.javiersc.either.network/-failure/-unknown/-unknown.html","searchKeys":["Unknown","fun Unknown(throwable: Throwable)","com.javiersc.either.network.Failure.Unknown.Unknown"]},{"name":"inline fun <F, S, L, R> NetworkEither<F, S>.toEither(left: (Failure<F>) -> L, right: (Success<S>) -> R): Either<L, R>","description":"com.javiersc.either.network.extensions.toEither","location":"projects/network/network-core/com.javiersc.either.network.extensions/to-either.html","searchKeys":["toEither","inline fun <F, S, L, R> NetworkEither<F, S>.toEither(left: (Failure<F>) -> L, right: (Success<S>) -> R): Either<L, R>","com.javiersc.either.network.extensions.toEither"]},{"name":"inline fun <F, S, L, R> NetworkEither<F, S>.toEither(success: (S) -> R, httpError: (F) -> L, localError: () -> L, remoteError: () -> L, unknownError: (Throwable) -> L): Either<L, R>","description":"com.javiersc.either.network.extensions.toEither","location":"projects/network/network-core/com.javiersc.either.network.extensions/to-either.html","searchKeys":["toEither","inline fun <F, S, L, R> NetworkEither<F, S>.toEither(success: (S) -> R, httpError: (F) -> L, localError: () -> L, remoteError: () -> L, unknownError: (Throwable) -> L): Either<L, R>","com.javiersc.either.network.extensions.toEither"]},{"name":"inline fun <F, S, L, R> NetworkEither<F, S>.toEither(success: (S) -> R, httpError: (HttpStatusCode) -> L, localError: () -> L, remoteError: () -> L, unknownError: (Throwable) -> L): Either<L, R>","description":"com.javiersc.either.network.extensions.toEither","location":"projects/network/network-core/com.javiersc.either.network.extensions/to-either.html","searchKeys":["toEither","inline fun <F, S, L, R> NetworkEither<F, S>.toEither(success: (S) -> R, httpError: (HttpStatusCode) -> L, localError: () -> L, remoteError: () -> L, unknownError: (Throwable) -> L): Either<L, R>","com.javiersc.either.network.extensions.toEither"]},{"name":"inline fun <F, S, L, R> NetworkEither<F, S>.toEither(success: (S, HttpStatusCode, Headers) -> R, httpError: (F, HttpStatusCode, Headers) -> L, localError: () -> L, remoteError: () -> L, unknownError: (Throwable) -> L): Either<L, R>","description":"com.javiersc.either.network.extensions.toEither","location":"projects/network/network-core/com.javiersc.either.network.extensions/to-either.html","searchKeys":["toEither","inline fun <F, S, L, R> NetworkEither<F, S>.toEither(success: (S, HttpStatusCode, Headers) -> R, httpError: (F, HttpStatusCode, Headers) -> L, localError: () -> L, remoteError: () -> L, unknownError: (Throwable) -> L): Either<L, R>","com.javiersc.either.network.extensions.toEither"]},{"name":"inline fun <F, S> NetworkEither<F, S>.fold(success: (S) -> Unit, failureHttp: (F) -> Unit, failureLocal: () -> Unit, failureRemote: () -> Unit, failureUnknown: (Throwable) -> Unit)","description":"com.javiersc.either.network.extensions.fold","location":"projects/network/network-core/com.javiersc.either.network.extensions/fold.html","searchKeys":["fold","inline fun <F, S> NetworkEither<F, S>.fold(success: (S) -> Unit, failureHttp: (F) -> Unit, failureLocal: () -> Unit, failureRemote: () -> Unit, failureUnknown: (Throwable) -> Unit)","com.javiersc.either.network.extensions.fold"]},{"name":"inline fun <F, S> NetworkEither<F, S>.fold(success: (S) -> Unit, failureHttp: (HttpStatusCode) -> Unit, failureLocal: () -> Unit, failureRemote: () -> Unit, failureUnknown: (Throwable) -> Unit)","description":"com.javiersc.either.network.extensions.fold","location":"projects/network/network-core/com.javiersc.either.network.extensions/fold.html","searchKeys":["fold","inline fun <F, S> NetworkEither<F, S>.fold(success: (S) -> Unit, failureHttp: (HttpStatusCode) -> Unit, failureLocal: () -> Unit, failureRemote: () -> Unit, failureUnknown: (Throwable) -> Unit)","com.javiersc.either.network.extensions.fold"]},{"name":"inline fun <F, S> NetworkEither<F, S>.fold(success: (S, HttpStatusCode, Headers) -> Unit, failureHttp: (F, HttpStatusCode, Headers) -> Unit, failureLocal: () -> Unit, failureRemote: () -> Unit, failureUnknown: (Throwable) -> Unit)","description":"com.javiersc.either.network.extensions.fold","location":"projects/network/network-core/com.javiersc.either.network.extensions/fold.html","searchKeys":["fold","inline fun <F, S> NetworkEither<F, S>.fold(success: (S, HttpStatusCode, Headers) -> Unit, failureHttp: (F, HttpStatusCode, Headers) -> Unit, failureLocal: () -> Unit, failureRemote: () -> Unit, failureUnknown: (Throwable) -> Unit)","com.javiersc.either.network.extensions.fold"]},{"name":"inline fun <F, S> NetworkEither<F, S>.foldOnlySuccessData(success: (S) -> Unit, failureHttp: () -> Unit, failureLocal: () -> Unit, failureRemote: () -> Unit, failureUnknown: (Throwable) -> Unit)","description":"com.javiersc.either.network.extensions.foldOnlySuccessData","location":"projects/network/network-core/com.javiersc.either.network.extensions/fold-only-success-data.html","searchKeys":["foldOnlySuccessData","inline fun <F, S> NetworkEither<F, S>.foldOnlySuccessData(success: (S) -> Unit, failureHttp: () -> Unit, failureLocal: () -> Unit, failureRemote: () -> Unit, failureUnknown: (Throwable) -> Unit)","com.javiersc.either.network.extensions.foldOnlySuccessData"]},{"name":"inline fun <F, S> NetworkEither<F, S>.ifFailure(block: (Failure<F>) -> Unit)","description":"com.javiersc.either.network.extensions.ifFailure","location":"projects/network/network-core/com.javiersc.either.network.extensions/if-failure.html","searchKeys":["ifFailure","inline fun <F, S> NetworkEither<F, S>.ifFailure(block: (Failure<F>) -> Unit)","com.javiersc.either.network.extensions.ifFailure"]},{"name":"inline fun <F, S> NetworkEither<F, S>.ifFailureHttp(block: (F, HttpStatusCode, Headers) -> Unit)","description":"com.javiersc.either.network.extensions.ifFailureHttp","location":"projects/network/network-core/com.javiersc.either.network.extensions/if-failure-http.html","searchKeys":["ifFailureHttp","inline fun <F, S> NetworkEither<F, S>.ifFailureHttp(block: (F, HttpStatusCode, Headers) -> Unit)","com.javiersc.either.network.extensions.ifFailureHttp"]},{"name":"inline fun <F, S> NetworkEither<F, S>.ifFailureHttpOnlyCode(block: (HttpStatusCode) -> Unit)","description":"com.javiersc.either.network.extensions.ifFailureHttpOnlyCode","location":"projects/network/network-core/com.javiersc.either.network.extensions/if-failure-http-only-code.html","searchKeys":["ifFailureHttpOnlyCode","inline fun <F, S> NetworkEither<F, S>.ifFailureHttpOnlyCode(block: (HttpStatusCode) -> Unit)","com.javiersc.either.network.extensions.ifFailureHttpOnlyCode"]},{"name":"inline fun <F, S> NetworkEither<F, S>.ifFailureHttpOnlyError(block: (F) -> Unit)","description":"com.javiersc.either.network.extensions.ifFailureHttpOnlyError","location":"projects/network/network-core/com.javiersc.either.network.extensions/if-failure-http-only-error.html","searchKeys":["ifFailureHttpOnlyError","inline fun <F, S> NetworkEither<F, S>.ifFailureHttpOnlyError(block: (F) -> Unit)","com.javiersc.either.network.extensions.ifFailureHttpOnlyError"]},{"name":"inline fun <F, S> NetworkEither<F, S>.ifFailureLocal(block: () -> Unit)","description":"com.javiersc.either.network.extensions.ifFailureLocal","location":"projects/network/network-core/com.javiersc.either.network.extensions/if-failure-local.html","searchKeys":["ifFailureLocal","inline fun <F, S> NetworkEither<F, S>.ifFailureLocal(block: () -> Unit)","com.javiersc.either.network.extensions.ifFailureLocal"]},{"name":"inline fun <F, S> NetworkEither<F, S>.ifFailureRemote(block: () -> Unit)","description":"com.javiersc.either.network.extensions.ifFailureRemote","location":"projects/network/network-core/com.javiersc.either.network.extensions/if-failure-remote.html","searchKeys":["ifFailureRemote","inline fun <F, S> NetworkEither<F, S>.ifFailureRemote(block: () -> Unit)","com.javiersc.either.network.extensions.ifFailureRemote"]},{"name":"inline fun <F, S> NetworkEither<F, S>.ifFailureUnknown(block: (Throwable) -> Unit)","description":"com.javiersc.either.network.extensions.ifFailureUnknown","location":"projects/network/network-core/com.javiersc.either.network.extensions/if-failure-unknown.html","searchKeys":["ifFailureUnknown","inline fun <F, S> NetworkEither<F, S>.ifFailureUnknown(block: (Throwable) -> Unit)","com.javiersc.either.network.extensions.ifFailureUnknown"]},{"name":"inline fun <F, S> NetworkEither<F, S>.ifSuccess(block: (S, HttpStatusCode, Headers) -> Unit)","description":"com.javiersc.either.network.extensions.ifSuccess","location":"projects/network/network-core/com.javiersc.either.network.extensions/if-success.html","searchKeys":["ifSuccess","inline fun <F, S> NetworkEither<F, S>.ifSuccess(block: (S, HttpStatusCode, Headers) -> Unit)","com.javiersc.either.network.extensions.ifSuccess"]},{"name":"inline fun <F, S> NetworkEither<F, S>.ifSuccessOnlyData(block: (S) -> Unit)","description":"com.javiersc.either.network.extensions.ifSuccessOnlyData","location":"projects/network/network-core/com.javiersc.either.network.extensions/if-success-only-data.html","searchKeys":["ifSuccessOnlyData","inline fun <F, S> NetworkEither<F, S>.ifSuccessOnlyData(block: (S) -> Unit)","com.javiersc.either.network.extensions.ifSuccessOnlyData"]},{"name":"inline suspend operator fun <F, S> invoke(request: HttpClient.() -> HttpResponse): NetworkEither<F, S>","description":"com.javiersc.either.network.ktor.NetworkEitherKtor.invoke","location":"projects/network/network-core/com.javiersc.either.network.ktor/-network-either-ktor/invoke.html","searchKeys":["invoke","inline suspend operator fun <F, S> invoke(request: HttpClient.() -> HttpResponse): NetworkEither<F, S>","com.javiersc.either.network.ktor.NetworkEitherKtor.invoke"]},{"name":"object Local : Failure<Nothing> ","description":"com.javiersc.either.network.Failure.Local","location":"projects/network/network-core/com.javiersc.either.network/-failure/-local/index.html","searchKeys":["Local","object Local : Failure<Nothing> ","com.javiersc.either.network.Failure.Local"]},{"name":"object Remote : Failure<Nothing> ","description":"com.javiersc.either.network.Failure.Remote","location":"projects/network/network-core/com.javiersc.either.network/-failure/-remote/index.html","searchKeys":["Remote","object Remote : Failure<Nothing> ","com.javiersc.either.network.Failure.Remote"]},{"name":"open operator override fun get(returnType: Type, annotations: Array<Annotation>, retrofit: Retrofit): CallAdapter<*, *>?","description":"com.javiersc.either.network.NetworkEitherCallAdapterFactory.get","location":"projects/network/network-core/com.javiersc.either.network/-network-either-call-adapter-factory/get.html","searchKeys":["get","open operator override fun get(returnType: Type, annotations: Array<Annotation>, retrofit: Retrofit): CallAdapter<*, *>?","com.javiersc.either.network.NetworkEitherCallAdapterFactory.get"]},{"name":"sealed class Failure<out F>","description":"com.javiersc.either.network.Failure","location":"projects/network/network-core/com.javiersc.either.network/-failure/index.html","searchKeys":["Failure","sealed class Failure<out F>","com.javiersc.either.network.Failure"]},{"name":"val code: HttpStatusCode","description":"com.javiersc.either.network.Failure.Http.code","location":"projects/network/network-core/com.javiersc.either.network/-failure/-http/code.html","searchKeys":["code","val code: HttpStatusCode","com.javiersc.either.network.Failure.Http.code"]},{"name":"val code: HttpStatusCode","description":"com.javiersc.either.network.Success.code","location":"projects/network/network-core/com.javiersc.either.network/-success/code.html","searchKeys":["code","val code: HttpStatusCode","com.javiersc.either.network.Success.code"]},{"name":"val data: S","description":"com.javiersc.either.network.Success.data","location":"projects/network/network-core/com.javiersc.either.network/-success/data.html","searchKeys":["data","val data: S","com.javiersc.either.network.Success.data"]},{"name":"val error: F","description":"com.javiersc.either.network.Failure.Http.error","location":"projects/network/network-core/com.javiersc.either.network/-failure/-http/error.html","searchKeys":["error","val error: F","com.javiersc.either.network.Failure.Http.error"]},{"name":"val headers: Headers","description":"com.javiersc.either.network.Failure.Http.headers","location":"projects/network/network-core/com.javiersc.either.network/-failure/-http/headers.html","searchKeys":["headers","val headers: Headers","com.javiersc.either.network.Failure.Http.headers"]},{"name":"val headers: Headers","description":"com.javiersc.either.network.Success.headers","location":"projects/network/network-core/com.javiersc.either.network/-success/headers.html","searchKeys":["headers","val headers: Headers","com.javiersc.either.network.Success.headers"]},{"name":"val isNetworkAvailable: Boolean","description":"com.javiersc.either.network.utils.isNetworkAvailable","location":"projects/network/network-core/com.javiersc.either.network.utils/is-network-available.html","searchKeys":["isNetworkAvailable","val isNetworkAvailable: Boolean","com.javiersc.either.network.utils.isNetworkAvailable"]},{"name":"val throwable: Throwable","description":"com.javiersc.either.network.Failure.Unknown.throwable","location":"projects/network/network-core/com.javiersc.either.network/-failure/-unknown/throwable.html","searchKeys":["throwable","val throwable: Throwable","com.javiersc.either.network.Failure.Unknown.throwable"]},{"name":"val value: Int","description":"com.javiersc.either.network.HttpStatusCode.value","location":"projects/network/network-core/com.javiersc.either.network/-http-status-code/value.html","searchKeys":["value","val value: Int","com.javiersc.either.network.HttpStatusCode.value"]},{"name":"data class Failure<F, S>(failure: F, data: S?, isLoading: Boolean)","description":"com.javiersc.either.resource.Failure","location":"projects/resource-core/com.javiersc.either.resource/-failure/index.html","searchKeys":["Failure","data class Failure<F, S>(failure: F, data: S?, isLoading: Boolean)","com.javiersc.either.resource.Failure"]},{"name":"data class Success<out S>(data: S, isLoading: Boolean)","description":"com.javiersc.either.resource.Success","location":"projects/resource-core/com.javiersc.either.resource/-success/index.html","searchKeys":["Success","data class Success<out S>(data: S, isLoading: Boolean)","com.javiersc.either.resource.Success"]},{"name":"fun <F, S> F.asFailure(data: S? = null, isLoading: Boolean = false): ResourceEither<F, S>","description":"com.javiersc.either.resource.extensions.asFailure","location":"projects/resource-core/com.javiersc.either.resource.extensions/as-failure.html","searchKeys":["asFailure","fun <F, S> F.asFailure(data: S? = null, isLoading: Boolean = false): ResourceEither<F, S>","com.javiersc.either.resource.extensions.asFailure"]},{"name":"fun <F, S> Failure(failure: F, data: S? = null, isLoading: Boolean = false)","description":"com.javiersc.either.resource.Failure.Failure","location":"projects/resource-core/com.javiersc.either.resource/-failure/-failure.html","searchKeys":["Failure","fun <F, S> Failure(failure: F, data: S? = null, isLoading: Boolean = false)","com.javiersc.either.resource.Failure.Failure"]},{"name":"fun <F, S> ResourceEither<F, S>.successDataOrNull(): S?","description":"com.javiersc.either.resource.extensions.successDataOrNull","location":"projects/resource-core/com.javiersc.either.resource.extensions/success-data-or-null.html","searchKeys":["successDataOrNull","fun <F, S> ResourceEither<F, S>.successDataOrNull(): S?","com.javiersc.either.resource.extensions.successDataOrNull"]},{"name":"fun <F, S> ResourceEither<F, S>.successOrNull(): ResourceSuccess<S>?","description":"com.javiersc.either.resource.extensions.successOrNull","location":"projects/resource-core/com.javiersc.either.resource.extensions/success-or-null.html","searchKeys":["successOrNull","fun <F, S> ResourceEither<F, S>.successOrNull(): ResourceSuccess<S>?","com.javiersc.either.resource.extensions.successOrNull"]},{"name":"fun <F, S> S.asSuccess(isLoading: Boolean = false): ResourceEither<F, S>","description":"com.javiersc.either.resource.extensions.asSuccess","location":"projects/resource-core/com.javiersc.either.resource.extensions/as-success.html","searchKeys":["asSuccess","fun <F, S> S.asSuccess(isLoading: Boolean = false): ResourceEither<F, S>","com.javiersc.either.resource.extensions.asSuccess"]},{"name":"fun <F, S> S.asSuccessLoading(): ResourceEither<F, S>","description":"com.javiersc.either.resource.extensions.asSuccessLoading","location":"projects/resource-core/com.javiersc.either.resource.extensions/as-success-loading.html","searchKeys":["asSuccessLoading","fun <F, S> S.asSuccessLoading(): ResourceEither<F, S>","com.javiersc.either.resource.extensions.asSuccessLoading"]},{"name":"fun <F, S> buildResourceFailure(failure: F, data: S? = null, isLoading: Boolean = false): ResourceEither<F, S>","description":"com.javiersc.either.resource.buildResourceFailure","location":"projects/resource-core/com.javiersc.either.resource/build-resource-failure.html","searchKeys":["buildResourceFailure","fun <F, S> buildResourceFailure(failure: F, data: S? = null, isLoading: Boolean = false): ResourceEither<F, S>","com.javiersc.either.resource.buildResourceFailure"]},{"name":"fun <F, S> buildResourceFailureLoading(failure: F, data: S? = null): ResourceEither<F, S>","description":"com.javiersc.either.resource.buildResourceFailureLoading","location":"projects/resource-core/com.javiersc.either.resource/build-resource-failure-loading.html","searchKeys":["buildResourceFailureLoading","fun <F, S> buildResourceFailureLoading(failure: F, data: S? = null): ResourceEither<F, S>","com.javiersc.either.resource.buildResourceFailureLoading"]},{"name":"fun <F, S> buildResourceSuccess(data: S, isLoading: Boolean = false): ResourceEither<F, S>","description":"com.javiersc.either.resource.buildResourceSuccess","location":"projects/resource-core/com.javiersc.either.resource/build-resource-success.html","searchKeys":["buildResourceSuccess","fun <F, S> buildResourceSuccess(data: S, isLoading: Boolean = false): ResourceEither<F, S>","com.javiersc.either.resource.buildResourceSuccess"]},{"name":"fun <F, S> buildResourceSuccessLoading(data: S): ResourceEither<F, S>","description":"com.javiersc.either.resource.buildResourceSuccessLoading","location":"projects/resource-core/com.javiersc.either.resource/build-resource-success-loading.html","searchKeys":["buildResourceSuccessLoading","fun <F, S> buildResourceSuccessLoading(data: S): ResourceEither<F, S>","com.javiersc.either.resource.buildResourceSuccessLoading"]},{"name":"fun <out S> Success(data: S, isLoading: Boolean = false)","description":"com.javiersc.either.resource.Success.Success","location":"projects/resource-core/com.javiersc.either.resource/-success/-success.html","searchKeys":["Success","fun <out S> Success(data: S, isLoading: Boolean = false)","com.javiersc.either.resource.Success.Success"]},{"name":"inline fun <F, S, NF, NS> Failure<F, S>.map(failure: (F) -> NF, fallbackData: (S?) -> NS? = { null }, isLoading: Boolean? = null): Failure<NF, NS>","description":"com.javiersc.either.resource.extensions.map","location":"projects/resource-core/com.javiersc.either.resource.extensions/map.html","searchKeys":["map","inline fun <F, S, NF, NS> Failure<F, S>.map(failure: (F) -> NF, fallbackData: (S?) -> NS? = { null }, isLoading: Boolean? = null): Failure<NF, NS>","com.javiersc.either.resource.extensions.map"]},{"name":"inline fun <F, S, NF, NS> ResourceEither<F, S>.map(failure: (F) -> NF, fallbackData: (S?) -> NS? = { null }, success: (S) -> NS, isLoading: Boolean? = null): ResourceEither<NF, NS>","description":"com.javiersc.either.resource.extensions.map","location":"projects/resource-core/com.javiersc.either.resource.extensions/map.html","searchKeys":["map","inline fun <F, S, NF, NS> ResourceEither<F, S>.map(failure: (F) -> NF, fallbackData: (S?) -> NS? = { null }, success: (S) -> NS, isLoading: Boolean? = null): ResourceEither<NF, NS>","com.javiersc.either.resource.extensions.map"]},{"name":"inline fun <F, S> ResourceEither<F, S>.fold(failure: (F, S?, Boolean) -> Unit, success: (S, Boolean) -> Unit)","description":"com.javiersc.either.resource.extensions.fold","location":"projects/resource-core/com.javiersc.either.resource.extensions/fold.html","searchKeys":["fold","inline fun <F, S> ResourceEither<F, S>.fold(failure: (F, S?, Boolean) -> Unit, success: (S, Boolean) -> Unit)","com.javiersc.either.resource.extensions.fold"]},{"name":"inline fun <F, S> ResourceEither<F, S>.ifFailure(failure: (F, S?, Boolean) -> Unit)","description":"com.javiersc.either.resource.extensions.ifFailure","location":"projects/resource-core/com.javiersc.either.resource.extensions/if-failure.html","searchKeys":["ifFailure","inline fun <F, S> ResourceEither<F, S>.ifFailure(failure: (F, S?, Boolean) -> Unit)","com.javiersc.either.resource.extensions.ifFailure"]},{"name":"inline fun <F, S> ResourceEither<F, S>.ifSuccess(data: (S, Boolean) -> Unit)","description":"com.javiersc.either.resource.extensions.ifSuccess","location":"projects/resource-core/com.javiersc.either.resource.extensions/if-success.html","searchKeys":["ifSuccess","inline fun <F, S> ResourceEither<F, S>.ifSuccess(data: (S, Boolean) -> Unit)","com.javiersc.either.resource.extensions.ifSuccess"]},{"name":"inline fun <S, NS> Success<S>.map(isLoading: Boolean? = null, data: (S) -> NS): Success<NS>","description":"com.javiersc.either.resource.extensions.map","location":"projects/resource-core/com.javiersc.either.resource.extensions/map.html","searchKeys":["map","inline fun <S, NS> Success<S>.map(isLoading: Boolean? = null, data: (S) -> NS): Success<NS>","com.javiersc.either.resource.extensions.map"]},{"name":"val <F, S> ResourceEither<F, S>.isFailure: Boolean","description":"com.javiersc.either.resource.extensions.isFailure","location":"projects/resource-core/com.javiersc.either.resource.extensions/is-failure.html","searchKeys":["isFailure","val <F, S> ResourceEither<F, S>.isFailure: Boolean","com.javiersc.either.resource.extensions.isFailure"]},{"name":"val <F, S> ResourceEither<F, S>.isLoading: Boolean","description":"com.javiersc.either.resource.extensions.isLoading","location":"projects/resource-core/com.javiersc.either.resource.extensions/is-loading.html","searchKeys":["isLoading","val <F, S> ResourceEither<F, S>.isLoading: Boolean","com.javiersc.either.resource.extensions.isLoading"]},{"name":"val <F, S> ResourceEither<F, S>.isSuccess: Boolean","description":"com.javiersc.either.resource.extensions.isSuccess","location":"projects/resource-core/com.javiersc.either.resource.extensions/is-success.html","searchKeys":["isSuccess","val <F, S> ResourceEither<F, S>.isSuccess: Boolean","com.javiersc.either.resource.extensions.isSuccess"]},{"name":"val data: S","description":"com.javiersc.either.resource.Success.data","location":"projects/resource-core/com.javiersc.either.resource/-success/data.html","searchKeys":["data","val data: S","com.javiersc.either.resource.Success.data"]},{"name":"val data: S? = null","description":"com.javiersc.either.resource.Failure.data","location":"projects/resource-core/com.javiersc.either.resource/-failure/data.html","searchKeys":["data","val data: S? = null","com.javiersc.either.resource.Failure.data"]},{"name":"val failure: F","description":"com.javiersc.either.resource.Failure.failure","location":"projects/resource-core/com.javiersc.either.resource/-failure/failure.html","searchKeys":["failure","val failure: F","com.javiersc.either.resource.Failure.failure"]},{"name":"val isLoading: Boolean = false","description":"com.javiersc.either.resource.Failure.isLoading","location":"projects/resource-core/com.javiersc.either.resource/-failure/is-loading.html","searchKeys":["isLoading","val isLoading: Boolean = false","com.javiersc.either.resource.Failure.isLoading"]},{"name":"val isLoading: Boolean = false","description":"com.javiersc.either.resource.Success.isLoading","location":"projects/resource-core/com.javiersc.either.resource/-success/is-loading.html","searchKeys":["isLoading","val isLoading: Boolean = false","com.javiersc.either.resource.Success.isLoading"]},{"name":"fun <F, S> NetworkEither<F, S>.alsoPrettyPrint(tag: String = \"NetworkEither\", failureSerializer: KSerializer<F>, successSerializer: KSerializer<S>): NetworkEither<F, S>","description":"com.javiersc.either.network.logger.alsoPrettyPrint","location":"projects/network/network-logger/com.javiersc.either.network.logger/also-pretty-print.html","searchKeys":["alsoPrettyPrint","fun <F, S> NetworkEither<F, S>.alsoPrettyPrint(tag: String = \"NetworkEither\", failureSerializer: KSerializer<F>, successSerializer: KSerializer<S>): NetworkEither<F, S>","com.javiersc.either.network.logger.alsoPrettyPrint"]},{"name":"inline fun <F, S> NetworkEither<F, S>.alsoPrettyPrint(tag: String = \"NetworkEither\"): NetworkEither<F, S>","description":"com.javiersc.either.network.logger.alsoPrettyPrint","location":"projects/network/network-logger/com.javiersc.either.network.logger/also-pretty-print.html","searchKeys":["alsoPrettyPrint","inline fun <F, S> NetworkEither<F, S>.alsoPrettyPrint(tag: String = \"NetworkEither\"): NetworkEither<F, S>","com.javiersc.either.network.logger.alsoPrettyPrint"]},{"name":"inline fun <NF, NS, F, S> NetworkEither<NF, NS>.toResource(left: (Failure<NF>) -> ResourceEither<F, S>, right: (Success<NS>) -> ResourceEither<F, S>): ResourceEither<F, S>","description":"com.javiersc.either.network.resource.toResource","location":"projects/network/network-resource/com.javiersc.either.network.resource/to-resource.html","searchKeys":["toResource","inline fun <NF, NS, F, S> NetworkEither<NF, NS>.toResource(left: (Failure<NF>) -> ResourceEither<F, S>, right: (Success<NS>) -> ResourceEither<F, S>): ResourceEither<F, S>","com.javiersc.either.network.resource.toResource"]},{"name":"inline fun <NF, NS, F, S> NetworkEither<NF, NS>.toResource(success: (NS) -> S, httpError: (HttpStatusCode) -> F, localError: () -> F, remoteError: () -> F, unknownError: (Throwable) -> F, isLoading: Boolean = false): ResourceEither<F, S>","description":"com.javiersc.either.network.resource.toResource","location":"projects/network/network-resource/com.javiersc.either.network.resource/to-resource.html","searchKeys":["toResource","inline fun <NF, NS, F, S> NetworkEither<NF, NS>.toResource(success: (NS) -> S, httpError: (HttpStatusCode) -> F, localError: () -> F, remoteError: () -> F, unknownError: (Throwable) -> F, isLoading: Boolean = false): ResourceEither<F, S>","com.javiersc.either.network.resource.toResource"]},{"name":"inline fun <NF, NS, F, S> NetworkEither<NF, NS>.toResource(success: (NS) -> S, httpError: (NF) -> F, localError: () -> F, remoteError: () -> F, unknownError: (Throwable) -> F, isLoading: Boolean = false): ResourceEither<F, S>","description":"com.javiersc.either.network.resource.toResource","location":"projects/network/network-resource/com.javiersc.either.network.resource/to-resource.html","searchKeys":["toResource","inline fun <NF, NS, F, S> NetworkEither<NF, NS>.toResource(success: (NS) -> S, httpError: (NF) -> F, localError: () -> F, remoteError: () -> F, unknownError: (Throwable) -> F, isLoading: Boolean = false): ResourceEither<F, S>","com.javiersc.either.network.resource.toResource"]},{"name":"inline fun <NF, NS, F, S> NetworkEither<NF, NS>.toResource(success: (NS, HttpStatusCode, Headers) -> S, httpError: (NF, HttpStatusCode, Headers) -> F, localError: () -> F, remoteError: () -> F, unknownError: (Throwable) -> F, isLoading: Boolean = false): ResourceEither<F, S>","description":"com.javiersc.either.network.resource.toResource","location":"projects/network/network-resource/com.javiersc.either.network.resource/to-resource.html","searchKeys":["toResource","inline fun <NF, NS, F, S> NetworkEither<NF, NS>.toResource(success: (NS, HttpStatusCode, Headers) -> S, httpError: (NF, HttpStatusCode, Headers) -> F, localError: () -> F, remoteError: () -> F, unknownError: (Throwable) -> F, isLoading: Boolean = false): ResourceEither<F, S>","com.javiersc.either.network.resource.toResource"]}]