{"version":"3","listProblem":[{
  "tool": "Code Inspection",
  "category": "Redundant constructs",
  "type": "Unused symbol",
  "tags": [
    "kotlin"
  ],
  "severity": "High",
  "comment": "Function \"successDataOrNull\" is never used",
  "detailsInfo": "Reports symbols that are not used or not reachable from entry points.",
  "sources": [
    {
      "type": "method",
      "path": "projects/resource-core/commonMain/kotlin/com/javiersc/either/resource/extensions/ResourceOr.kt",
      "language": "kotlin",
      "line": 9,
      "offset": 39,
      "length": 17,
      "code": {
        "startLine": 7,
        "length": 17,
        "offset": 91,
        "surroundingCode": "    if (this is ResourceSuccess<S>) this else null\n\npublic fun <F, S> ResourceEither<F, S>.successDataOrNull(): S? =\n    if (this is ResourceSuccess<S>) right.data else null"
      }
    }
  ],
  "attributes": {
    "module": "either.projects.resource-core.commonMain",
    "inspectionName": "UnusedSymbol"
  },
  "hash": "-2195170149349149491"
},{
  "tool": "Code Inspection",
  "category": "Redundant constructs",
  "type": "Unused symbol",
  "tags": [
    "kotlin"
  ],
  "severity": "High",
  "comment": "Function \"successOrNull\" is never used",
  "detailsInfo": "Reports symbols that are not used or not reachable from entry points.",
  "sources": [
    {
      "type": "method",
      "path": "projects/resource-core/commonMain/kotlin/com/javiersc/either/resource/extensions/ResourceOr.kt",
      "language": "kotlin",
      "line": 6,
      "offset": 39,
      "length": 13,
      "code": {
        "startLine": 4,
        "length": 13,
        "offset": 92,
        "surroundingCode": "import com.javiersc.either.resource.ResourceSuccess\n\npublic fun <F, S> ResourceEither<F, S>.successOrNull(): ResourceSuccess<S>? =\n    if (this is ResourceSuccess<S>) this else null\n"
      }
    }
  ],
  "attributes": {
    "module": "either.projects.resource-core.commonMain",
    "inspectionName": "UnusedSymbol"
  },
  "hash": "-4078336491634993750"
},{
  "tool": "Code Inspection",
  "category": "Redundant constructs",
  "type": "Unused symbol",
  "tags": [
    "kotlin"
  ],
  "severity": "High",
  "comment": "Function \"map\" is never used",
  "detailsInfo": "Reports symbols that are not used or not reachable from entry points.",
  "sources": [
    {
      "type": "method",
      "path": "projects/resource-core/commonMain/kotlin/com/javiersc/either/resource/extensions/ResourceEitherMap.kt",
      "language": "kotlin",
      "line": 26,
      "offset": 47,
      "length": 3,
      "code": {
        "startLine": 24,
        "length": 3,
        "offset": 54,
        "surroundingCode": "    }\n\npublic inline fun <F, S, NF, NS> Failure<F, S>.map(\n    failure: (F) -> NF,\n    fallbackData: (S?) -> NS? = { null },"
      }
    }
  ],
  "attributes": {
    "module": "either.projects.resource-core.commonMain",
    "inspectionName": "UnusedSymbol"
  },
  "hash": "-4839184018641717124"
},{
  "tool": "Code Inspection",
  "category": "Redundant constructs",
  "type": "Unused symbol",
  "tags": [
    "kotlin"
  ],
  "severity": "High",
  "comment": "Function \"map\" is never used",
  "detailsInfo": "Reports symbols that are not used or not reachable from entry points.",
  "sources": [
    {
      "type": "method",
      "path": "projects/resource-core/commonMain/kotlin/com/javiersc/either/resource/extensions/ResourceEitherMap.kt",
      "language": "kotlin",
      "line": 33,
      "offset": 37,
      "length": 3,
      "code": {
        "startLine": 31,
        "length": 3,
        "offset": 127,
        "surroundingCode": "    Failure(failure(this.failure), fallbackData(this.data), isLoading ?: this.isLoading)\n\npublic inline fun <S, NS> Success<S>.map(isLoading: Boolean? = null, data: (S) -> NS): Success<NS> =\n    Success(data(this.data), isLoading ?: this.isLoading)"
      }
    }
  ],
  "attributes": {
    "module": "either.projects.resource-core.commonMain",
    "inspectionName": "UnusedSymbol"
  },
  "hash": "-8392039999114015316"
}]}